Metadata-Version: 2.1
Name: something-with-pokemon
Version: 0.0
Summary: Pokemon thing
Author-email: cstawer2005@mail.ru
